adv_speedtest_cli-2.1.0.dist-info/licenses/LICENSE
advanced_speedtest_cli/__init__.py
advanced_speedtest_cli/__main__.py
advanced_speedtest_cli/speedtest.py
adv_speedtest_cli-2.1.0.dist-info/METADATA
adv_speedtest_cli-2.1.0.dist-info/WHEEL
adv_speedtest_cli-2.1.0.dist-info/entry_points.txt
adv_speedtest_cli-2.1.0.dist-info/top_level.txt
adv_speedtest_cli-2.1.0.dist-info/RECORD
