Metadata-Version: 2.4
Name: adv-speedtest-cli
Version: 2.1.0
Summary: A sophisticated cross-platform command-line utility for measuring internet speed with precision
Home-page: https://github.com/shakilofficial0/adv-speedtest-cli
Author: Shakil Ahmed
Author-email: Shakil Ahmed <shakilofficial0@gmail.com>
License: MIT
Project-URL: Homepage, https://github.com/shakilofficial0/adv-speedtest-cli
Project-URL: Documentation, https://github.com/shakilofficial0/adv-speedtest-cli#readme
Project-URL: Repository, https://github.com/shakilofficial0/adv-speedtest-cli.git
Project-URL: Bug Tracker, https://github.com/shakilofficial0/adv-speedtest-cli/issues
Keywords: speedtest,internet-speed,bandwidth,network,cli,speed-measurement,download-upload-ping,network-diagnostics,cross-platform
Classifier: Environment :: Console
Classifier: Intended Audience :: End Users/Desktop
Classifier: Intended Audience :: Developers
Classifier: Intended Audience :: System Administrators
Classifier: License :: OSI Approved :: MIT License
Classifier: Natural Language :: English
Classifier: Operating System :: OS Independent
Classifier: Operating System :: Microsoft :: Windows
Classifier: Operating System :: MacOS
Classifier: Operating System :: POSIX :: Linux
Classifier: Programming Language :: Python :: 3
Classifier: Programming Language :: Python :: 3.7
Classifier: Programming Language :: Python :: 3.8
Classifier: Programming Language :: Python :: 3.9
Classifier: Programming Language :: Python :: 3.10
Classifier: Programming Language :: Python :: 3.11
Classifier: Programming Language :: Python :: 3.12
Classifier: Programming Language :: Python :: 3 :: Only
Classifier: Topic :: System :: Networking
Classifier: Topic :: Utilities
Classifier: Development Status :: 5 - Production/Stable
Requires-Python: >=3.7
License-File: LICENSE
Requires-Dist: tqdm>=4.62.0
Requires-Dist: requests>=2.26.0
Requires-Dist: click>=8.0.0
Requires-Dist: colorama>=0.4.4
Requires-Dist: validators>=0.18.0
Requires-Dist: websockets>=10.0
Dynamic: author
Dynamic: home-page
Dynamic: license-file
Dynamic: requires-python
